arkologger/__init__.py
arkologger/_config.py
arkologger/_file.py
arkologger/_handler.py
arkologger/_logger.py
arkologger/_style.py
arkologger/_traceback.py
arko_logger-0.1.3.dist-info/LICENSE.txt
arko_logger-0.1.3.dist-info/METADATA
arko_logger-0.1.3.dist-info/WHEEL
arko_logger-0.1.3.dist-info/RECORD
